[
  {
    "maskFrame" : null,
    "visible" : true,
    "id" : "C63F2AEE-A8AC-40F5-99D5-3D8105231710",
    "children" : [
      {
        "maskFrame" : null,
        "visible" : true,
        "id" : "CEB83BE7-3714-4805-9E50-976B8C5BC8F7",
        "children" : [

        ],
        "image" : {
          "path" : "images\/ButtonCards-CEB83BE7-3714-4805-9E50-976B8C5BC8F7.png",
          "frame" : {
            "y" : 66,
            "x" : 564,
            "width" : 52,
            "height" : 48
          }
        },
        "imageType" : "png",
        "layerFrame" : {
          "y" : 66,
          "x" : 564,
          "width" : 52,
          "height" : 48
        },
        "name" : "ButtonCards"
      },
      {
        "maskFrame" : null,
        "visible" : true,
        "id" : "EC588742-CCE0-44EC-BB95-25B1E02617C1",
        "children" : [

        ],
        "image" : {
          "path" : "images\/ButtonHelp-EC588742-CCE0-44EC-BB95-25B1E02617C1.png",
          "frame" : {
            "y" : 66,
            "x" : 24,
            "width" : 48,
            "height" : 48
          }
        },
        "imageType" : "png",
        "layerFrame" : {
          "y" : 66,
          "x" : 24,
          "width" : 48,
          "height" : 48
        },
        "name" : "ButtonHelp"
      },
      {
        "maskFrame" : null,
        "visible" : true,
        "id" : "19847EC2-E699-43E3-B5F1-71EEE3E6C0E4",
        "children" : [

        ],
        "image" : {
          "path" : "images\/Header-19847EC2-E699-43E3-B5F1-71EEE3E6C0E4.png",
          "frame" : {
            "y" : 0,
            "x" : -2,
            "width" : 644,
            "height" : 184
          }
        },
        "imageType" : "png",
        "layerFrame" : {
          "y" : 0,
          "x" : -2,
          "width" : 644,
          "height" : 184
        },
        "name" : "Header"
      },
      {
        "maskFrame" : null,
        "visible" : true,
        "id" : "62C9C93D-B2A7-4CCE-AC53-FC8513BC77B3",
        "children" : [

        ],
        "image" : {
          "path" : "images\/BgBg-62C9C93D-B2A7-4CCE-AC53-FC8513BC77B3.png",
          "frame" : {
            "y" : -10,
            "x" : -10,
            "width" : 660,
            "height" : 1156
          }
        },
        "imageType" : "png",
        "layerFrame" : {
          "y" : -10,
          "x" : -10,
          "width" : 660,
          "height" : 1156
        },
        "name" : "BgBg"
      }
    ],
    "image" : {
      "path" : "images\/Portrait-C63F2AEE-A8AC-40F5-99D5-3D8105231710.png",
      "frame" : {
        "y" : 0,
        "x" : 0,
        "width" : 640,
        "height" : 1136
      }
    },
    "imageType" : "png",
    "layerFrame" : {
      "y" : 0,
      "x" : 0,
      "width" : 640,
      "height" : 1136
    },
    "name" : "Portrait"
  }
]